{
  "project_info": {
    "project_number": "784990691438",
    "project_id": "grouping-project-cb62c",
    "storage_bucket": "grouping-project-cb62c.appspot.com"
  },
  "client": [
    {
      "client_info": {
        "mobilesdk_app_id": "1:784990691438:android:87acd91002d965598a467f",
        "android_client_info": {
          "package_name": "com.example.grouping_project"
        }
      },
      "oauth_client": [
        {
          "client_id": "784990691438-vutrcfkafr5d4eaq0tio9q36bl72bvae.apps.googleusercontent.com",
          "client_type": 1,
          "android_info": {
            "package_name": "com.example.grouping_project",
            "certificate_hash": "fe47540651eb2cd60bb2c4bf6243f223d9a2bf68"
          }
        },
        {
          "client_id": "784990691438-2raup8q9qutdb9cc4fq1cpg6ntffm0be.apps.googleusercontent.com",
          "client_type": 3
        }
      ],
      "api_key": [
        {
          "current_key": "AIzaSyB5CBpCZUJ9RG-r7td4qSCqE9Jo0zA2GDA"
        }
      ],
      "services": {
        "appinvite_service": {
          "other_platform_oauth_client": [
            {
              "client_id": "784990691438-2raup8q9qutdb9cc4fq1cpg6ntffm0be.apps.googleusercontent.com",
              "client_type": 3
            },
            {
              "client_id": "784990691438-q9ni6tteu6336u58fcdlf9opdm6cvtok.apps.googleusercontent.com",
              "client_type": 2,
              "ios_info": {
                "bundle_id": "com.example.groupingProject"
              }
            }
          ]
        }
      }
    }
  ],
  "configuration_version": "1"
}